LICENSE
README.rst
setup.py
fixie_batch/__init__.py
fixie_batch/environ.py
fixie_batch/handlers.py
fixie_batch/simulations.py
fixie_batch.egg-info/PKG-INFO
fixie_batch.egg-info/SOURCES.txt
fixie_batch.egg-info/dependency_links.txt
fixie_batch.egg-info/not-zip-safe
fixie_batch.egg-info/requires.txt
fixie_batch.egg-info/top_level.txt